build/lib/recall_space_benchmarks/__init__.py
build/lib/recall_space_benchmarks/session/__init__.py
build/lib/recall_space_benchmarks/session/message.py
build/lib/recall_space_benchmarks/session/session.py
build/lib/recall_space_benchmarks/session/langchain_session/__init__.py
build/lib/recall_space_benchmarks/session/langchain_session/langchain_session.py
build/lib/recall_space_benchmarks/test_suite/__init__.py
build/lib/recall_space_benchmarks/test_suite/test_suite.py
build/lib/recall_space_benchmarks/test_suite/tests/__init__.py
build/lib/recall_space_benchmarks/test_suite/tests/colors.py
build/lib/recall_space_benchmarks/test_suite/tests/directions.py
build/lib/recall_space_benchmarks/test_suite/tests/jokes.py
build/lib/recall_space_benchmarks/utils/__init__.py
build/lib/recall_space_benchmarks/utils/mongo_connector.py
build/lib/recall_space_benchmarks/utils/recall_space/memory_engine_connector.py
build/lib/recall_space_benchmarks/utils/recall_space/models_map.py
build/lib/recall_space_benchmarks/utils/recall_space/recall_space_agent.py
build/lib/recall_space_benchmarks/utils/recall_space/recall_space_tools.py
recall_space_benchmarks/__init__.py
recall_space_benchmarks/session/__init__.py
recall_space_benchmarks/session/message.py
recall_space_benchmarks/session/session.py
recall_space_benchmarks/session/langchain_session/__init__.py
recall_space_benchmarks/session/langchain_session/langchain_session.py
recall_space_benchmarks/test_suite/__init__.py
recall_space_benchmarks/test_suite/test_suite.py
recall_space_benchmarks/test_suite/tests/__init__.py
recall_space_benchmarks/test_suite/tests/colors.py
recall_space_benchmarks/test_suite/tests/directions.py
recall_space_benchmarks/test_suite/tests/jokes.py
recall_space_benchmarks/utils/__init__.py
recall_space_benchmarks/utils/mongo_connector.py
recall_space_benchmarks/utils/recall_space/memory_engine_connector.py
recall_space_benchmarks/utils/recall_space/models_map.py
recall_space_benchmarks-0.0.4.dist-info/LICENSE
recall_space_benchmarks-0.0.4.dist-info/METADATA
recall_space_benchmarks-0.0.4.dist-info/WHEEL
recall_space_benchmarks-0.0.4.dist-info/top_level.txt
recall_space_benchmarks-0.0.4.dist-info/RECORD
